ms_python_rust-0.1.0.dist-info/METADATA
ms_python_rust-0.1.0.dist-info/WHEEL
ms_python_rust-0.1.0.dist-info/licenses/LICENSE
ms_python_rust.libs/libgcc_s-98a1ef30.so.1
ms_python_rust/__init__.py
ms_python_rust/ms_python_rust.cpython-311-x86_64-linux-musl.so
ms_python_rust-0.1.0.dist-info/RECORD
