Metadata-Version: 2.4
Name: ms-python-rust
Version: 0.1.0
Classifier: Development Status :: 4 - Beta
Classifier: Intended Audience :: Developers
Classifier: License :: OSI Approved :: MIT License
Classifier: Programming Language :: Python
Classifier: Programming Language :: Python :: 3
Classifier: Programming Language :: Rust
Classifier: Topic :: Software Development :: Libraries
Classifier: Topic :: Utilities
Requires-Dist: pytest ; extra == 'dev'
Provides-Extra: dev
License-File: LICENSE
Summary: Tiny millisecond conversion utility for Python backed by Rust
Keywords: milliseconds,duration,time,conversion,rust,pyo3
Author: Jeremiah Barrar
Requires-Python: >=3.8
Project-URL: Homepage, https://github.com/barrar/ms-python-rust
Project-URL: Repository, https://github.com/barrar/ms-python-rust
